CHANGES.txt
bootstrap.py
buildout.cfg
setup.py
src/ice/__init__.py
src/ice.adverlet.egg-info/PKG-INFO
src/ice.adverlet.egg-info/SOURCES.txt
src/ice.adverlet.egg-info/dependency_links.txt
src/ice.adverlet.egg-info/namespace_packages.txt
src/ice.adverlet.egg-info/not-zip-safe
src/ice.adverlet.egg-info/requires.txt
src/ice.adverlet.egg-info/top_level.txt
src/ice/adverlet/LICENSE.txt
src/ice/adverlet/README.txt
src/ice/adverlet/__init__.py
src/ice/adverlet/adverlet.py
src/ice/adverlet/configure.zcml
src/ice/adverlet/events.py
src/ice/adverlet/i18n.py
src/ice/adverlet/image.py
src/ice/adverlet/interfaces.py
src/ice/adverlet/meta.zcml
src/ice/adverlet/metaconfigure.py
src/ice/adverlet/metadirectives.py
src/ice/adverlet/storage.py
src/ice/adverlet/tales.py
src/ice/adverlet/vocabulary.py
src/ice/adverlet/browser/__init__.py
src/ice/adverlet/browser/configure.zcml
src/ice/adverlet/browser/help.pt
src/ice/adverlet/browser/interfaces.py
src/ice/adverlet/browser/manage.pt
src/ice/adverlet/browser/manage.py
src/ice/adverlet/browser/template.py
src/ice/adverlet/browser/undo.pt
src/ice/adverlet/browser/undo.py
src/ice/adverlet/browser/widget.py
src/ice/adverlet/browser/resources/manage.css
src/ice/adverlet/browser/resources/text-bg.gif
src/ice/adverlet/demo/README.txt
src/ice/adverlet/demo/__init__.py
src/ice/adverlet/demo/app.py
src/ice/adverlet/demo/app.zcml
src/ice/adverlet/demo/browser.py
src/ice/adverlet/demo/configure.zcml
src/ice/adverlet/demo/frontpage.pt
src/ice/adverlet/demo/layout.pt
src/ice/adverlet/demo/manage.pt
src/ice/adverlet/locales/ice.adverlet.pot
src/ice/adverlet/tests/__init__.py
src/ice/adverlet/tests/browser.zcml
src/ice/adverlet/tests/ftesting.zcml
src/ice/adverlet/tests/ftests.py
src/ice/adverlet/tests/ftests.txt
src/ice/adverlet/tests/sampledata.py
src/ice/adverlet/tests/sampledata.zcml
src/ice/adverlet/tests/template.pt
src/ice/adverlet/tests/tests.py