Metadata-Version: 1.0
Name: ice.adverlet
Version: 0.2.3
Summary: Simple way to edit any HTML snippet
Home-page: http://launchpad.net/ice.adverlet
Author: Ilshad Habibullin
Author-email: astoon.net at gmail.com
License: GPL v.3
Platform: UNKNOWN
Classifier: Development Status :: 3 - Alpha
Classifier: Environment :: Web Environment
Classifier: Intended Audience :: Developers
Classifier: License :: OSI Approved :: GNU General Public License (GPL)
Classifier: Programming Language :: Python
Classifier: Natural Language :: English
Classifier: Operating System :: OS Independent
Classifier: Topic :: Internet :: WWW/HTTP :: Site Management
Classifier: Framework :: Zope3
